webp_imagefield/__init__.py
webp_imagefield/fields.py
webpimagefield/__init__.py
webp_imagefield-0.2.2.dist-info/LICENSE
webp_imagefield-0.2.2.dist-info/METADATA
webp_imagefield-0.2.2.dist-info/WHEEL
webp_imagefield-0.2.2.dist-info/top_level.txt
webp_imagefield-0.2.2.dist-info/RECORD
